litetokenscli/__init__.py
litetokenscli/cli.py
litetokenscli/constants.py
litetokenscli/h_config.py
litetokenscli/h_init.py
litetokenscli/h_status.py
litetokenscli/h_worker.py
litetokenscli/json_store.py
litetokenscli/utils.py
litetokenscli-0.1.4.data/scripts/litetokens-cli
litetokenscli-0.1.4.dist-info/LICENSE
litetokenscli-0.1.4.dist-info/METADATA
litetokenscli-0.1.4.dist-info/WHEEL
litetokenscli-0.1.4.dist-info/top_level.txt
litetokenscli-0.1.4.dist-info/RECORD
