Metadata-Version: 2.1
Name: litetokenscli
Version: 0.1.4
Summary: A command line tool to monitor and manage litetokens nodes.
Home-page: https://github.com/litetokensprotocol/litetokens-cli
Author: Weiyu X
Author-email: weiyu@litetokens.network
License: UNKNOWN
Platform: UNKNOWN
Classifier: Environment :: Console
Classifier: License :: OSI Approved :: MIT License
Classifier: Operating System :: OS Independent
Classifier: Programming Language :: Python :: 3
Classifier: Programming Language :: Python :: 3.4
Classifier: Programming Language :: Python :: 3.5
Requires-Dist: bleach (==3.0.2)
Requires-Dist: cbox (==0.5.0)
Requires-Dist: certifi (==2018.10.15)
Requires-Dist: chardet (==3.0.4)
Requires-Dist: colorama (==0.4.0)
Requires-Dist: docutils (==0.14)
Requires-Dist: idna (==2.7)
Requires-Dist: pkginfo (==1.4.2)
Requires-Dist: psutil (==5.4.7)
Requires-Dist: Pygments (==2.2.0)
Requires-Dist: readme-renderer (==24.0)
Requires-Dist: requests (==2.20.0)
Requires-Dist: requests-toolbelt (==0.8.0)
Requires-Dist: six (==1.11.0)
Requires-Dist: tqdm (==4.28.1)
Requires-Dist: litetokenscli (==0.1.3)
Requires-Dist: twine (==1.12.1)
Requires-Dist: urllib3 (==1.24)
Requires-Dist: webencodings (==0.5.1)
